django_rq_pulse/__init__.py
django_rq_pulse/apps.py
django_rq_pulse/models.py
django_rq_pulse/urls.py
django_rq_pulse/views.py
django_rq_pulse/management/__init__.py
django_rq_pulse/management/commands/__init__.py
django_rq_pulse/management/commands/rq_pulse_check.py
django_rq_pulse/static/css/django_rq_pulse.css
django_rq_pulse/static/js/django_rq_pulse.js
django_rq_pulse/templates/django_rq_pulse/base.html
django_rq_pulse-0.2.0.dist-info/AUTHORS.rst
django_rq_pulse-0.2.0.dist-info/METADATA
django_rq_pulse-0.2.0.dist-info/WHEEL
django_rq_pulse-0.2.0.dist-info/top_level.txt
django_rq_pulse-0.2.0.dist-info/RECORD
