Metadata-Version: 2.1
Name: django-rq-pulse
Version: 0.2.0
Summary: A Django package to check that rq workers are running and notify admins if they are not
Home-page: https://github.com/NZME/django-rq-pulse
Author: Medhat Gayed
Author-email: medhat.gayed@nzme.co.nz
License: MIT
Keywords: django-rq-pulse
Platform: UNKNOWN
Classifier: Development Status :: 3 - Alpha
Classifier: Framework :: Django
Classifier: Framework :: Django :: 1.8
Classifier: Framework :: Django :: 1.9
Classifier: Framework :: Django :: 1.11
Classifier: Framework :: Django :: 2.2
Classifier: Intended Audience :: Developers
Classifier: License :: OSI Approved :: BSD License
Classifier: Natural Language :: English
Classifier: Programming Language :: Python :: 2
Classifier: Programming Language :: Python :: 2.7
Classifier: Programming Language :: Python :: 3
Classifier: Programming Language :: Python :: 3.5
Classifier: Programming Language :: Python :: 3.6
